Workbook

Sheet Summary
A1: Securitized Products Surveillance Pack
A2: Synthetic RMBS Pool 2026-1 · generated 2026-08-13
A3: All data is synthetic and generated for demonstration. RWA is a simplified rating-band proxy, not SEC-SA / SEC-IRBA.
A5: Pool metric | B5: Value
A6: Loan count | B6: 2000
A7: Current UPB | B7: 4.8888503e+08
A8: WA coupon (%) | B8: 6.383
A9: WA FICO | B9: 715
A10: WA LTV (%) | B10: 74
A11: WA DTI (%) | B11: 35.9
A12: WA seasoning (mo) | B12: 24
A15: Projected performance | B15: Value
A16: Average CPR | B16: 0.098549445
A17: Average CDR (GNN-adjusted) | B17: 0.014335484
A18: GNN risk multiplier | B18: 1.371475
A19: Cumulative loss (base) | B19: 6166284.3
A20: Total RWA | B20: 1.9660345e+08
A21: Total expected loss | B21: 894632.55
A24: Escalations
A25: ESCALATION: scenario S1 (Credit stress (rising unemployment, HPI decline)) projects cumulative loss of 2.49% of UPB, above the 2.0% desk threshold.
A29: Contents
A30: Assumptions | B30: Inputs, risk weights, model validation
A31: Loan Tape | B31: Loan-level collateral data
A32: Stratification | B32: FICO / LTV / geography cuts (live formulas)
A33: Pool Cashflows | B33: Projected monthly cashflows, base case
A34: Waterfall | B34: Tranche principal, interest, balances
A35: Exposure & RWA | B35: EAD, PD, LGD, EL, RWA
A36: Scenario Stress | B36: Generated scenarios and escalation flags

Sheet Assumptions
A1: Surveillance Assumptions & Model Inputs
A2: Blue cells are hardcoded inputs. Every downstream sheet references them.
A4: Assumption | B4: Value | D4: Note
A5: Deal | B5: Synthetic RMBS Pool 2026-1 | D5: Demonstration pool — synthetic data
A6: Projection horizon (months) | B6: 36 | D6: Surveillance projection window
A7: Loss severity (LGD) | B7: 0.35 | D7: Applied to defaulted balance
A8: Escalation threshold (% UPB) | B8: 0.02 | D8: Cumulative loss above this escalates to desk
A9: Senior tranche size | B9: 0.78 | D9: Capital structure — Class A
A10: Mezzanine tranche size | B10: 0.14 | D10: Capital structure — Class M
A11: Subordinate tranche size | B11: 0.08 | D11: Capital structure — Class B
A15: Standardized-approach risk weights
A16: Simplified rating-band proxy — not a full SEC-SA / SEC-IRBA implementation.
A17: Rating | B17: Risk weight
A18: AAA | B18: 0.2
A19: AA | B19: 0.2
A20: A | B20: 0.5
A21: BBB | B21: 1
A22: BB | B22: 2.5
A23: B | B23: 4.25
A24: Unrated | B24: 12.5
A27: Model validation (holdout, 400 unseen sequences)
A28: Metric | B28: CPR | C28: CDR
A29: R² | B29: 0.8642 | C29: 0.9746
A30: MAE | B30: 0.00453 | C30: 0.00037
A31: Predicted sd | C31: 0.00369
A32: Realised sd | C32: 0.00374

Sheet Loan Tape
A1: Loan-Level Collateral Tape
A2: 2,000 loans. Source data for every stratification on this workbook.
A4: loan_id | B4: orig_balance | C4: current_balance | D4: coupon | E4: fico | F4: ltv | G4: dti | H4: seasoning_mo | I4: remaining_term_mo | J4: state | K4: property_type | L4: originator | M4: servicer
A5: L100000 | B5: 270127.94 | C5: 259045.88 | D5: 6.7 | E5: 690 | F5: 77 | G5: 37.8 | H5: 42 | I5: 318 | J5: NY | K5: SFR | L5: Meridian Home Loans | M5: Pier Asset Mgmt
A6: L100001 | B6: 168721.64 | C6: 163539.79 | D6: 7.513 | E6: 678 | F6: 84.7 | G6: 35.6 | H6: 37 | I6: 323 | J6: AZ | K6: SFR | L6: Highline Capital | M6: Northgate Servicing
A7: L100002 | B7: 315734.81 | C7: 307167 | D7: 7.494 | E7: 739 | F7: 77.3 | G7: 42.9 | H7: 33 | I7: 327 | J7: WA | K7: Multifamily | L7: Apex Funding | M7: Northgate Servicing
A8: L100003 | B8: 337458.44 | C8: 333309.77 | D8: 5.994 | E8: 729 | F8: 97 | G8: 40.9 | H8: 12 | I8: 348 | J8: FL | K8: SFR | L8: Meridian Home Loans | M8: Summit Loan Servicing
A9: L100004 | B9: 122655.84 | C9: 119103.27 | D9: 6.575 | E9: 638 | F9: 91.2 | G9: 12.1 | H9: 30 | I9: 330 | J9: NC | K9: SFR | L9: Coastal Mortgage Co | M9: Pier Asset Mgmt
A10: L100005 | B10: 153927.53 | C10: 129137.16 | D10: 4.722 | E10: 777 | F10: 70.3 | G10: 40.4 | H10: 39 | I10: 141 | J10: TX | K10: SFR | L10: Highline Capital | M10: Pier Asset Mgmt
A11: L100006 | B11: 253912.28 | C11: 252984.67 | D11: 6.489 | E11: 710 | F11: 70.2 | G11: 28 | H11: 4 | I11: 356 | J11: NY | K11: SFR | L11: Coastal Mortgage Co | M11: Summit Loan Servicing
A12: L100007 | B12: 217361.05 | C12: 210319.52 | D12: 5.685 | E12: 654 | F12: 79.6 | G12: 24.6 | H12: 9 | I12: 171 | J12: NC | K12: SFR | L12: Coastal Mortgage Co | M12: Northgate Servicing
A13: L100008 | B13: 241378.04 | C13: 235259.67 | D13: 6.232 | E13: 780 | F13: 63.9 | G13: 34.5 | H13: 25 | I13: 335 | J13: FL | K13: 2-4 Unit | L13: Meridian Home Loans | M13: Northgate Servicing
A14: L100009 | B14: 180130.1 | C14: 176245.48 | D14: 4.883 | E14: 749 | F14: 88 | G14: 39.3 | H14: 17 | I14: 343 | J14: FL | K14: SFR | L14: Meridian Home Loans | M14: Summit Loan Servicing
A15: L100010 | B15: 330310.79 | C15: 319714.78 | D15: 6.764 | E15: 645 | F15: 78.3 | G15: 22.9 | H15: 34 | I15: 326 | J15: NY | K15: SFR | L15: Highline Capital | M15: Summit Loan Servicing
A16: L100011 | B16: 318770.66 | C16: 311042.13 | D16: 4.873 | E16: 813 | F16: 77.1 | G16: 41.6 | H16: 19 | I16: 341 | J16: TX | K16: SFR | L16: Highline Capital | M16: Summit Loan Servicing
... A2004: L101999 | B2004: 526998.73 | C2004: 505380.32 | D2004: 6.235 | E2004: 646 | F2004: 57.4 | G2004: 38 | H2004: 39 | I2004: 321 | J2004: FL | K2004: SFR | L2004: Apex Funding | M2004: Pier Asset Mgmt

Sheet Stratification
A1: Collateral Stratification
A2: Every figure below is a live formula over the Loan Tape (SUMIFS / SUMPRODUCT). Edit the tape and these update.
A4: By FICO
A5: Bucket | B5: Loan count | C5: UPB | D5: % of pool | E5: WA coupon | F5: WA LTV
A6: <620 | B6: =COUNTIFS('Loan Tape'!$E$5:$E$2004,">=0",'Loan Tape'!$E$5:$E$2004,"<620") | C6: =SUMIFS('Loan Tape'!$C$5:$C$2004,'Loan Tape'!$E$5:$E$2004,">=0",'Loan Tape'!$E$5:$E$2004,"<620") | D6: =IFERROR(C6/$C$12,0) | E6: =IFERROR(SUMPRODUCT(('Loan Tape'!$E$5:$E$2004>=0)*('Loan Tape'!$E$5:$E$2004<620)*'Loan Tape'!$C$5:$C$2004*'Loan Tape'!$D$5:$D$2004)/C6,0) | F6: =IFERROR(SUMPRODUCT(('Loan Tape'!$E$5:$E$2004>=0)*('Loan Tape'!$E$5:$E$2004<620)*'Loan Tape'!$C$5:$C$2004*'Loan Tape'!$F$5:$F$2004)/C6,0)
A7: 620-659 | B7: =COUNTIFS('Loan Tape'!$E$5:$E$2004,">=620",'Loan Tape'!$E$5:$E$2004,"<660") | C7: =SUMIFS('Loan Tape'!$C$5:$C$2004,'Loan Tape'!$E$5:$E$2004,">=620",'Loan Tape'!$E$5:$E$2004,"<660") | D7: =IFERROR(C7/$C$12,0) | E7: =IFERROR(SUMPRODUCT(('Loan Tape'!$E$5:$E$2004>=620)*('Loan Tape'!$E$5:$E$2004<660)*'Loan Tape'!$C$5:$C$2004*'Loan Tape'!$D$5:$D$2004)/C7,0) | F7: =IFERROR(SUMPRODUCT(('Loan Tape'!$E$5:$E$2004>=620)*('Loan Tape'!$E$5:$E$2004<660)*'Loan Tape'!$C$5:$C$2004*'Loan Tape'!$F$5:$F$2004)/C7,0)
A8: 660-699 | B8: =COUNTIFS('Loan Tape'!$E$5:$E$2004,">=660",'Loan Tape'!$E$5:$E$2004,"<700") | C8: =SUMIFS('Loan Tape'!$C$5:$C$2004,'Loan Tape'!$E$5:$E$2004,">=660",'Loan Tape'!$E$5:$E$2004,"<700") | D8: =IFERROR(C8/$C$12,0) | E8: =IFERROR(SUMPRODUCT(('Loan Tape'!$E$5:$E$2004>=660)*('Loan Tape'!$E$5:$E$2004<700)*'Loan Tape'!$C$5:$C$2004*'Loan Tape'!$D$5:$D$2004)/C8,0) | F8: =IFERROR(SUMPRODUCT(('Loan Tape'!$E$5:$E$2004>=660)*('Loan Tape'!$E$5:$E$2004<700)*'Loan Tape'!$C$5:$C$2004*'Loan Tape'!$F$5:$F$2004)/C8,0)
A9: 700-739 | B9: =COUNTIFS('Loan Tape'!$E$5:$E$2004,">=700",'Loan Tape'!$E$5:$E$2004,"<740") | C9: =SUMIFS('Loan Tape'!$C$5:$C$2004,'Loan Tape'!$E$5:$E$2004,">=700",'Loan Tape'!$E$5:$E$2004,"<740") | D9: =IFERROR(C9/$C$12,0) | E9: =IFERROR(SUMPRODUCT(('Loan Tape'!$E$5:$E$2004>=700)*('Loan Tape'!$E$5:$E$2004<740)*'Loan Tape'!$C$5:$C$2004*'Loan Tape'!$D$5:$D$2004)/C9,0) | F9: =IFERROR(SUMPRODUCT(('Loan Tape'!$E$5:$E$2004>=700)*('Loan Tape'!$E$5:$E$2004<740)*'Loan Tape'!$C$5:$C$2004*'Loan Tape'!$F$5:$F$2004)/C9,0)
A10: 740-779 | B10: =COUNTIFS('Loan Tape'!$E$5:$E$2004,">=740",'Loan Tape'!$E$5:$E$2004,"<780") | C10: =SUMIFS('Loan Tape'!$C$5:$C$2004,'Loan Tape'!$E$5:$E$2004,">=740",'Loan Tape'!$E$5:$E$2004,"<780") | D10: =IFERROR(C10/$C$12,0) | E10: =IFERROR(SUMPRODUCT(('Loan Tape'!$E$5:$E$2004>=740)*('Loan Tape'!$E$5:$E$2004<780)*'Loan Tape'!$C$5:$C$2004*'Loan Tape'!$D$5:$D$2004)/C10,0) | F10: =IFERROR(SUMPRODUCT(('Loan Tape'!$E$5:$E$2004>=740)*('Loan Tape'!$E$5:$E$2004<780)*'Loan Tape'!$C$5:$C$2004*'Loan Tape'!$F$5:$F$2004)/C10,0)
A11: 780+ | B11: =COUNTIFS('Loan Tape'!$E$5:$E$2004,">=780",'Loan Tape'!$E$5:$E$2004,"<10000") | C11: =SUMIFS('Loan Tape'!$C$5:$C$2004,'Loan Tape'!$E$5:$E$2004,">=780",'Loan Tape'!$E$5:$E$2004,"<10000") | D11: =IFERROR(C11/$C$12,0) | E11: =IFERROR(SUMPRODUCT(('Loan Tape'!$E$5:$E$2004>=780)*('Loan Tape'!$E$5:$E$2004<10000)*'Loan Tape'!$C$5:$C$2004*'Loan Tape'!$D$5:$D$2004)/C11,0) | F11: =IFERROR(SUMPRODUCT(('Loan Tape'!$E$5:$E$2004>=780)*('Loan Tape'!$E$5:$E$2004<10000)*'Loan Tape'!$C$5:$C$2004*'Loan Tape'!$F$5:$F$2004)/C11,0)
A12: Total | B12: =SUM(B6:B11) | C12: =SUM(C6:C11) | D12: =SUM(D6:D11)
A15: By LTV
A16: Bucket | B16: Loan count | C16: UPB | D16: % of pool | E16: WA coupon | F16: WA FICO
A17: <60 | B17: =COUNTIFS('Loan Tape'!$F$5:$F$2004,">=0",'Loan Tape'!$F$5:$F$2004,"<60") | C17: =SUMIFS('Loan Tape'!$C$5:$C$2004,'Loan Tape'!$F$5:$F$2004,">=0",'Loan Tape'!$F$5:$F$2004,"<60") | D17: =IFERROR(C17/$C$23,0) | E17: =IFERROR(SUMPRODUCT(('Loan Tape'!$F$5:$F$2004>=0)*('Loan Tape'!$F$5:$F$2004<60)*'Loan Tape'!$C$5:$C$2004*'Loan Tape'!$D$5:$D$2004)/C17,0) | F17: =IFERROR(SUMPRODUCT(('Loan Tape'!$F$5:$F$2004>=0)*('Loan Tape'!$F$5:$F$2004<60)*'Loan Tape'!$C$5:$C$2004*'Loan Tape'!$E$5:$E$2004)/C17,0)
A18: 60-69 | B18: =COUNTIFS('Loan Tape'!$F$5:$F$2004,">=60",'Loan Tape'!$F$5:$F$2004,"<70") | C18: =SUMIFS('Loan Tape'!$C$5:$C$2004,'Loan Tape'!$F$5:$F$2004,">=60",'Loan Tape'!$F$5:$F$2004,"<70") | D18: =IFERROR(C18/$C$23,0) | E18: =IFERROR(SUMPRODUCT(('Loan Tape'!$F$5:$F$2004>=60)*('Loan Tape'!$F$5:$F$2004<70)*'Loan Tape'!$C$5:$C$2004*'Loan Tape'!$D$5:$D$2004)/C18,0) | F18: =IFERROR(SUMPRODUCT(('Loan Tape'!$F$5:$F$2004>=60)*('Loan Tape'!$F$5:$F$2004<70)*'Loan Tape'!$C$5:$C$2004*'Loan Tape'!$E$5:$E$2004)/C18,0)
A19: 70-79 | B19: =COUNTIFS('Loan Tape'!$F$5:$F$2004,">=70",'Loan Tape'!$F$5:$F$2004,"<80") | C19: =SUMIFS('Loan Tape'!$C$5:$C$2004,'Loan Tape'!$F$5:$F$2004,">=70",'Loan Tape'!$F$5:$F$2004,"<80") | D19: =IFERROR(C19/$C$23,0) | E19: =IFERROR(SUMPRODUCT(('Loan Tape'!$F$5:$F$2004>=70)*('Loan Tape'!$F$5:$F$2004<80)*'Loan Tape'!$C$5:$C$2004*'Loan Tape'!$D$5:$D$2004)/C19,0) | F19: =IFERROR(SUMPRODUCT(('Loan Tape'!$F$5:$F$2004>=70)*('Loan Tape'!$F$5:$F$2004<80)*'Loan Tape'!$C$5:$C$2004*'Loan Tape'!$E$5:$E$2004)/C19,0)
A20: 80-89 | B20: =COUNTIFS('Loan Tape'!$F$5:$F$2004,">=80",'Loan Tape'!$F$5:$F$2004,"<90") | C20: =SUMIFS('Loan Tape'!$C$5:$C$2004,'Loan Tape'!$F$5:$F$2004,">=80",'Loan Tape'!$F$5:$F$2004,"<90") | D20: =IFERROR(C20/$C$23,0) | E20: =IFERROR(SUMPRODUCT(('Loan Tape'!$F$5:$F$2004>=80)*('Loan Tape'!$F$5:$F$2004<90)*'Loan Tape'!$C$5:$C$2004*'Loan Tape'!$D$5:$D$2004)/C20,0) | F20: =IFERROR(SUMPRODUCT(('Loan Tape'!$F$5:$F$2004>=80)*('Loan Tape'!$F$5:$F$2004<90)*'Loan Tape'!$C$5:$C$2004*'Loan Tape'!$E$5:$E$2004)/C20,0)
A21: 90-99 | B21: =COUNTIFS('Loan Tape'!$F$5:$F$2004,">=90",'Loan Tape'!$F$5:$F$2004,"<100") | C21: =SUMIFS('Loan Tape'!$C$5:$C$2004,'Loan Tape'!$F$5:$F$2004,">=90",'Loan Tape'!$F$5:$F$2004,"<100") | D21: =IFERROR(C21/$C$23,0) | E21: =IFERROR(SUMPRODUCT(('Loan Tape'!$F$5:$F$2004>=90)*('Loan Tape'!$F$5:$F$2004<100)*'Loan Tape'!$C$5:$C$2004*'Loan Tape'!$D$5:$D$2004)/C21,0) | F21: =IFERROR(SUMPRODUCT(('Loan Tape'!$F$5:$F$2004>=90)*('Loan Tape'!$F$5:$F$2004<100)*'Loan Tape'!$C$5:$C$2004*'Loan Tape'!$E$5:$E$2004)/C21,0)
A22: 100+ | B22: =COUNTIFS('Loan Tape'!$F$5:$F$2004,">=100",'Loan Tape'!$F$5:$F$2004,"<1000") | C22: =SUMIFS('Loan Tape'!$C$5:$C$2004,'Loan Tape'!$F$5:$F$2004,">=100",'Loan Tape'!$F$5:$F$2004,"<1000") | D22: =IFERROR(C22/$C$23,0) | E22: =IFERROR(SUMPRODUCT(('Loan Tape'!$F$5:$F$2004>=100)*('Loan Tape'!$F$5:$F$2004<1000)*'Loan Tape'!$C$5:$C$2004*'Loan Tape'!$D$5:$D$2004)/C22,0) | F22: =IFERROR(SUMPRODUCT(('Loan Tape'!$F$5:$F$2004>=100)*('Loan Tape'!$F$5:$F$2004<1000)*'Loan Tape'!$C$5:$C$2004*'Loan Tape'!$E$5:$E$2004)/C22,0)
A23: Total | B23: =SUM(B17:B22) | C23: =SUM(C17:C22) | D23: =SUM(D17:D22)
A26: By state
A27: State | B27: Loan count | C27: UPB | D27: % of pool | E27: WA FICO
A28: AZ | B28: =COUNTIFS('Loan Tape'!$J$5:$J$2004,A28) | C28: =SUMIFS('Loan Tape'!$C$5:$C$2004,'Loan Tape'!$J$5:$J$2004,A28) | D28: =IFERROR(C28/$C$38,0) | E28: =IFERROR(SUMPRODUCT(('Loan Tape'!$J$5:$J$2004=A28)*'Loan Tape'!$C$5:$C$2004*'Loan Tape'!$E$5:$E$2004)/C28,0)
A29: CA | B29: =COUNTIFS('Loan Tape'!$J$5:$J$2004,A29) | C29: =SUMIFS('Loan Tape'!$C$5:$C$2004,'Loan Tape'!$J$5:$J$2004,A29) | D29: =IFERROR(C29/$C$38,0) | E29: =IFERROR(SUMPRODUCT(('Loan Tape'!$J$5:$J$2004=A29)*'Loan Tape'!$C$5:$C$2004*'Loan Tape'!$E$5:$E$2004)/C29,0)
A30: FL | B30: =COUNTIFS('Loan Tape'!$J$5:$J$2004,A30) | C30: =SUMIFS('Loan Tape'!$C$5:$C$2004,'Loan Tape'!$J$5:$J$2004,A30) | D30: =IFERROR(C30/$C$38,0) | E30: =IFERROR(SUMPRODUCT(('Loan Tape'!$J$5:$J$2004=A30)*'Loan Tape'!$C$5:$C$2004*'Loan Tape'!$E$5:$E$2004)/C30,0)
A31: GA | B31: =COUNTIFS('Loan Tape'!$J$5:$J$2004,A31) | C31: =SUMIFS('Loan Tape'!$C$5:$C$2004,'Loan Tape'!$J$5:$J$2004,A31) | D31: =IFERROR(C31/$C$38,0) | E31: =IFERROR(SUMPRODUCT(('Loan Tape'!$J$5:$J$2004=A31)*'Loan Tape'!$C$5:$C$2004*'Loan Tape'!$E$5:$E$2004)/C31,0)
A32: IL | B32: =COUNTIFS('Loan Tape'!$J$5:$J$2004,A32) | C32: =SUMIFS('Loan Tape'!$C$5:$C$2004,'Loan Tape'!$J$5:$J$2004,A32) | D32: =IFERROR(C32/$C$38,0) | E32: =IFERROR(SUMPRODUCT(('Loan Tape'!$J$5:$J$2004=A32)*'Loan Tape'!$C$5:$C$2004*'Loan Tape'!$E$5:$E$2004)/C32,0)
A33: NC | B33: =COUNTIFS('Loan Tape'!$J$5:$J$2004,A33) | C33: =SUMIFS('Loan Tape'!$C$5:$C$2004,'Loan Tape'!$J$5:$J$2004,A33) | D33: =IFERROR(C33/$C$38,0) | E33: =IFERROR(SUMPRODUCT(('Loan Tape'!$J$5:$J$2004=A33)*'Loan Tape'!$C$5:$C$2004*'Loan Tape'!$E$5:$E$2004)/C33,0)
A34: NY | B34: =COUNTIFS('Loan Tape'!$J$5:$J$2004,A34) | C34: =SUMIFS('Loan Tape'!$C$5:$C$2004,'Loan Tape'!$J$5:$J$2004,A34) | D34: =IFERROR(C34/$C$38,0) | E34: =IFERROR(SUMPRODUCT(('Loan Tape'!$J$5:$J$2004=A34)*'Loan Tape'!$C$5:$C$2004*'Loan Tape'!$E$5:$E$2004)/C34,0)
A35: OH | B35: =COUNTIFS('Loan Tape'!$J$5:$J$2004,A35) | C35: =SUMIFS('Loan Tape'!$C$5:$C$2004,'Loan Tape'!$J$5:$J$2004,A35) | D35: =IFERROR(C35/$C$38,0) | E35: =IFERROR(SUMPRODUCT(('Loan Tape'!$J$5:$J$2004=A35)*'Loan Tape'!$C$5:$C$2004*'Loan Tape'!$E$5:$E$2004)/C35,0)
A36: TX | B36: =COUNTIFS('Loan Tape'!$J$5:$J$2004,A36) | C36: =SUMIFS('Loan Tape'!$C$5:$C$2004,'Loan Tape'!$J$5:$J$2004,A36) | D36: =IFERROR(C36/$C$38,0) | E36: =IFERROR(SUMPRODUCT(('Loan Tape'!$J$5:$J$2004=A36)*'Loan Tape'!$C$5:$C$2004*'Loan Tape'!$E$5:$E$2004)/C36,0)
A37: WA | B37: =COUNTIFS('Loan Tape'!$J$5:$J$2004,A37) | C37: =SUMIFS('Loan Tape'!$C$5:$C$2004,'Loan Tape'!$J$5:$J$2004,A37) | D37: =IFERROR(C37/$C$38,0) | E37: =IFERROR(SUMPRODUCT(('Loan Tape'!$J$5:$J$2004=A37)*'Loan Tape'!$C$5:$C$2004*'Loan Tape'!$E$5:$E$2004)/C37,0)
A38: Total | B38: =SUM(B28:B37) | C38: =SUM(C28:C37) | D38: =SUM(D28:D37)

Sheet Pool Cashflows
A1: Projected Pool Cashflows — Base Case
A2: Model-projected. CPR/CDR from the Transformer forecaster, default losses at the severity on Assumptions.
A4: period | B4: scheduled_principal | C4: prepayment | D4: interest_collected | E4: loss | F4: ending_balance
A5: 1 | B5: 452104.05 | C5: 4531585.1 | D5: 2600461 | E5: 203317.12 | F5: 4.8369803e+08
A6: 2 | B6: 450102.83 | C6: 4488882 | D6: 2572870.4 | E6: 201555.93 | F6: 4.7855748e+08
A7: 3 | B7: 448105.03 | C7: 4447256 | D7: 2545527 | E7: 199896.49 | F7: 4.7346223e+08
A8: 4 | B8: 446109.89 | C8: 4407754.8 | D8: 2518424.5 | E8: 198272.67 | F8: 4.6841009e+08
A9: 5 | B9: 444115.69 | C9: 4371054.3 | D9: 2491551.3 | E9: 196671.4 | F9: 4.6339825e+08
A10: 6 | B10: 442120.03 | C10: 4337189.1 | D10: 2464892.5 | E10: 195056.12 | F10: 4.5842388e+08
A11: 7 | B11: 440120.46 | C11: 4302090.4 | D11: 2438433 | E11: 193183.24 | F11: 4.5348849e+08
A12: 8 | B12: 438118.61 | C12: 4255750.5 | D12: 2412180.9 | E12: 191103.43 | F12: 4.4860352e+08
A13: 9 | B13: 436125.87 | C13: 4209884.1 | D13: 2386196.9 | E13: 189044.87 | F13: 4.4376846e+08
A14: 10 | B14: 434142.19 | C14: 4164486.5 | D14: 2360478.4 | E14: 187007.34 | F14: 4.3898283e+08
A15: 11 | B15: 432167.53 | C15: 4119553 | D15: 2335022.8 | E15: 184990.64 | F15: 4.3424611e+08
A16: 12 | B16: 430201.85 | C16: 4075078.9 | D16: 2309827.5 | E16: 182994.55 | F16: 4.2955784e+08
... A40: 36 | B40: 385615.53 | C40: 3134249.8 | D40: 1776815.9 | E40: 140767.07 | F40: 3.3037965e+08
A41: Total | B41: =SUM(B5:B40) | C41: =SUM(C5:C40) | D41: =SUM(D5:D40) | E41: =SUM(E5:E40)

Sheet Waterfall
A1: Tranche Waterfall — Sequential Pay
A2: Interest pro-rata to outstanding balance; principal sequential senior→sub; losses reverse-sequential (subordinate absorbs first).
A4: Tranche summary
A5: tranche | B5: total_principal | C5: total_interest | D5: final_balance
A6: A (Senior) | B6: 1.523391e+08 | C6: 49943895 | D6: 2.2899123e+08
A7: B (Subordinate) | B7: 0 | C7: 6847691.3 | D7: 32944518
A8: M (Mezz) | B8: 0 | C8: 13111842 | D8: 68443904
A11: Period detail
A12: period | B12: tranche | C12: principal_paid | D12: interest_paid | E12: ending_balance
A13: 1 | B13: A (Senior) | C13: 4983689.1 | D13: 1747764 | E13: 3.7634664e+08
A14: 1 | B14: M (Mezz) | C14: 0 | D14: 364216.01 | E14: 68443904
A15: 1 | B15: B (Subordinate) | C15: 0 | D15: 207041.5 | E15: 38907485
A16: 2 | B16: A (Senior) | C16: 4938984.8 | D16: 1724922.1 | E16: 3.7140765e+08
A17: 2 | B17: M (Mezz) | C17: 0 | D17: 364216.3 | E17: 68443904
A18: 2 | B18: B (Subordinate) | C18: 0 | D18: 205969.12 | E18: 38705930
A19: 3 | B19: A (Senior) | C19: 4895361 | D19: 1702285.1 | E19: 3.6651229e+08
A20: 3 | B20: M (Mezz) | C20: 0 | D20: 364216.67 | E20: 68443904
A21: 3 | B21: B (Subordinate) | C21: 0 | D21: 204905.6 | E21: 38506033
A22: 4 | B22: A (Senior) | C22: 4853864.7 | D22: 1679848 | E22: 3.6165843e+08
A23: 4 | B23: M (Mezz) | C23: 0 | D23: 364217.06 | E23: 68443904
A24: 4 | B24: B (Subordinate) | C24: 0 | D24: 203850.73 | E24: 38307760
... A120: 36 | B120: B (Subordinate) | C120: 0 | D120: 175311.26 | E120: 32944518

Sheet Exposure & RWA
A1: Tranche Exposure, Expected Loss and RWA
A2: EL = EAD × PD × LGD and RWA = EAD × risk weight are live formulas. LGD and the risk-weight table live on Assumptions.
A4: Tranche | B4: Proxy rating | C4: EAD | D4: PD | E4: LGD | F4: Expected loss | G4: Risk weight | H4: RWA
A5: A (Senior) | B5: AAA | C5: 2.2899123e+08 | D5: 0.00215 | E5: =Assumptions!$B$7 | F5: =C5*D5*E5 | G5: =INDEX(Assumptions!$B$18:$B$24,MATCH(B5,Assumptions!$A$18:$A$24,0)) | H5: =C5*G5
A6: B (Subordinate) | B6: BB | C6: 32944518 | D6: 0.035839 | E6: =Assumptions!$B$7 | F6: =C6*D6*E6 | G6: =INDEX(Assumptions!$B$18:$B$24,MATCH(B6,Assumptions!$A$18:$A$24,0)) | H6: =C6*G6
A7: M (Mezz) | B7: BBB | C7: 68443904 | D7: 0.012902 | E7: =Assumptions!$B$7 | F7: =C7*D7*E7 | G7: =INDEX(Assumptions!$B$18:$B$24,MATCH(B7,Assumptions!$A$18:$A$24,0)) | H7: =C7*G7
A8: Total | C8: =SUM(C5:C7) | F8: =SUM(F5:F7) | H8: =SUM(H5:H7)

Sheet Scenario Stress
A1: VAE-Generated Scenario Stress | B1: 4.8888503e+08 | C1: ← pool UPB (denominator for loss %)
A2: Scenarios sampled from the latent space of a VAE trained on macro regime paths — generated, not hand-specified.
A4: Scenario | B4: Label | C4: Avg CPR | D4: Avg CDR | E4: Cumulative loss | F4: Loss % of UPB | G4: Sub write-down | H4: Escalates?
A5: S1 | B5: Credit stress (rising unemployment, HPI decline) | C5: 0.1131 | D5: 0.0291 | E5: 12173172 | F5: =E5/$B$1 | G5: 12173172 | H5: =IF(F5>Assumptions!$B$8,"ESCALATE","within tolerance")
A6: S2 | B6: Rate rally (elevated prepayment incentive) | C6: 0.1575 | D6: 0.0146 | E6: 5825826.2 | F6: =E6/$B$1 | G6: 5825826.2 | H6: =IF(F6>Assumptions!$B$8,"ESCALATE","within tolerance")
A7: S3 | B7: Base-like | C7: 0.0844 | D7: 0.0142 | E7: 6250229.2 | F7: =E7/$B$1 | G7: 6250229.2 | H7: =IF(F7>Assumptions!$B$8,"ESCALATE","within tolerance")
A8: S4 | B8: Base-like | C8: 0.1118 | D8: 0.0152 | E8: 6544150.6 | F8: =E8/$B$1 | G8: 6544150.6 | H8: =IF(F8>Assumptions!$B$8,"ESCALATE","within tolerance")
A9: S5 | B9: Rate rally (elevated prepayment incentive) | C9: 0.1232 | D9: 0.0142 | E9: 5988883.4 | F9: =E9/$B$1 | G9: 5988883.4 | H9: =IF(F9>Assumptions!$B$8,"ESCALATE","within tolerance")
